{
  "easycom": {
    "autoscan": true,
    "custom": {
      "^uni-(.*)": "@dcloudio/uni-ui/lib/uni-$1/uni-$1.vue",
      "^u-(.*)": "uview-ui/components/u-$1/u-$1.vue"
    }
  },
  "pages": [
    {
      "path": "pages/Home/index",
      "style": {
        "navigationBarTitleText": "首页"
      }
    },
    {
      "path": "pages/login/index",
      "style": {
        "navigationBarTitleText": "登录"
      }
    },
    {
      "path": "pages/Error/index",
      "style": {
        "navigationBarTitleText": "初始化失败"
      }
    },
    {
      "path": "pages/searchPage/index",
      "style": {
        "navigationBarTitleText": "搜索",
        "mp-weixin": {
          "homeButton": true
        }
      }
    },
    {
      "path": "pages/MenusSetting/index",
      "style": {
        "navigationBarTitleText": "所有功能",
        "mp-weixin": {
          "homeButton": true
        }
      }
    }
  ],
  "subPackages": [
    {
      "root": "Erp",
      "pages": [
        {
          "path": "Stock/index",
          "style": {
            "navigationBarTitleText": "仓储中心",
            "mp-weixin": {
              "homeButton": true
            }
          }
        },
        {
          "path": "Receipt/ReceiptList/index",
          "style": {
            "navigationBarTitleText": "任务列表",
            "mp-weixin": {
              "homeButton": true
            }
          }
        },
        {
          "path": "Receipt/ReceiptDetail/index",
          "style": {
            "navigationBarTitleText": "审批详情",
            "mp-weixin": {
              "homeButton": true
            }
          }
        },
        {
          "path": "OutStock/OutStockDetail/index",
          "style": {
            "navigationBarTitleText": "出库详情",
            "mp-weixin": {
              "homeButton": true
            }
          }
        },
        {
          "path": "OutStock/OutStockAction/index",
          "style": {
            "navigationBarTitleText": "出库操作",
            "mp-weixin": {
              "homeButton": true
            }
          }
        },
        {
          "path": "OutStock/OutStockConfirm/index",
          "style": {
            "navigationBarTitleText": "出库确认",
            "mp-weixin": {
              "homeButton": true
            }
          }
        },
        {
          "path": "InStock/InStockAsk/index",
          "style": {
            "navigationBarTitleText": "入库申请",
            "mp-weixin": {
              "homeButton": true
            }
          }
        },
        {
          "path": "InStock/InStockAction/index",
          "style": {
            "navigationBarTitleText": "入库申请",
            "mp-weixin": {
              "homeButton": true
            }
          }
        },
        {
          "path": "Stocktaking/immediately/index",
          "style": {
            "navigationBarTitleText": "即时盘点",
            "mp-weixin": {
              "homeButton": true
            }
          }
        },
        {
          "path": "Stocktaking/immediatelyDetail/index",
          "style": {
            "navigationBarTitleText": "即时盘点",
            "mp-weixin": {
              "homeButton": true
            }
          }
        },
        {
          "path": "InStock/InStockVoucher/index",
          "style": {
            "navigationBarTitleText": "入库凭证",
            "mp-weixin": {
              "homeButton": true
            }
          }
        },
        {
          "path": "StockForewarn/index",
          "style": {
            "navigationBarTitleText": "库存预警",
            "mp-weixin": {
              "homeButton": true
            }
          }
        }
      ]
    },
    {
      "root": "Purchase",
      "pages": [
        {
          "path": "Order/OrderList/index",
          "style": {
            "navigationBarTitleText": "订单列表",
            "mp-weixin": {
              "homeButton": true
            }
          }
        },
        {
          "path": "Order/OrderDetail/index",
          "style": {
            "navigationBarTitleText": "订单详情",
            "mp-weixin": {
              "homeButton": true
            }
          }
        },
        {
          "path": "Order/ConfirmArrival/index",
          "style": {
            "navigationBarTitleText": "确认到货",
            "mp-weixin": {
              "homeButton": true
            }
          }
        }
      ]
    },
    {
      "root": "Production",
      "pages": [
        {
          "path": "Information/index",
          "style": {
            "navigationBarTitleText": "选择产品信息",
            "mp-weixin": {
              "homeButton": true
            }
          }
        },
        {
          "path": "CreatePlan/index",
          "style": {
            "navigationBarTitleText": "创建生产计划",
            "mp-weixin": {
              "homeButton": true
            }
          }
        },
        {
          "path": "BomDetailList/index",
          "style": {
            "navigationBarTitleText": "创建生产计划",
            "mp-weixin": {
              "homeButton": true
            }
          }
        },
        {
          "path": "Produced/index",
          "style": {
            "navigationBarTitleText": "待生产",
            "mp-weixin": {
              "homeButton": true
            }
          }
        }
      ]
    },
    {
      "root": "Sku",
      "pages": [
        {
          "path": "SkuDetail/index",
          "style": {
            "navigationBarTitleText": "物料详情",
            "mp-weixin": {
              "homeButton": true
            }
          }
        },
        {
          "path": "SkuImgs/index",
          "style": {
            "navigationBarTitleText": "物料图片",
            "mp-weixin": {
              "homeButton": true
            }
          }
        },
        {
          "path": "SkuDetailWebView/index",
          "style": {
            "navigationBarTitleText": "物料详情",
            "mp-weixin": {
              "homeButton": true
            }
          }
        }
      ]
    },
    {
      "root": "User",
      "pages": [
        {
          "path": "SelectUser/index",
          "style": {
            "navigationBarTitleText": "企业通讯录",
            "mp-weixin": {
              "homeButton": true
            }
          }
        }
      ]
    }
  ],
  "globalStyle": {
    "navigationBarTextStyle": "black",
    "navigationBarBackgroundColor": "#F8F8F8",
    "backgroundColor": "#F8F8F8",
    "usingComponents": {
      "van-button": "/wxcomponents/button/index",
      "van-cascader": "/wxcomponents/cascader/index",
      "van-toast": "/wxcomponents/toast/index",
      "van-loading": "/wxcomponents/loading/index",
      "van-overlay": "/wxcomponents/overlay/index",
      "van-dialog": "/wxcomponents/dialog/index",
      "van-skeleton": "/wxcomponents/skeleton/index",
      "van-tab": "/wxcomponents/tab/index",
      "van-tabs": "/wxcomponents/tabs/index",
      "van-icon": "/wxcomponents/icon/index",
      "van-divider": "/wxcomponents/divider/index",
      "van-swipe-cell": "/wxcomponents/swipe-cell/index",
      "van-empty": "/wxcomponents/empty/index",
      "van-checkbox": "/wxcomponents/checkbox/index",
      "van-checkbox-group": "/wxcomponents/checkbox-group/index",
      "van-popup": "/wxcomponents/popup/index",
      "van-field": "/wxcomponents/field/index",
      "van-stepper": "/wxcomponents/van-stepper/index",
      "van-uploader": "/wxcomponents/vant-uploader/index",
      "van-picker": "/wxcomponents/vant-picker/index",
      "van-search": "/wxcomponents/search/index",
      "van-tabbar": "/wxcomponents/tabbar/index",
      "van-tabbar-item": "/wxcomponents/tabbar-item/index",
      "van-datetime-picker": "/wxcomponents/datetime-picker/index",
      "van-dropdown-menu": "/wxcomponents/dropdown-menu/index",
      "van-dropdown-item": "/wxcomponents/dropdown-item/index",
      "van-radio": "/wxcomponents/vant-radio/index",
      "van-radio-group": "/wxcomponents/vant-radio-group/index"
    }
  }
}
